OpsworksTool-0.0.2.dist-info/METADATA
OpsworksTool-0.0.2.dist-info/RECORD
OpsworksTool-0.0.2.dist-info/WHEEL
OpsworksTool-0.0.2.dist-info/entry_points.txt
OpsworksTool-0.0.2.dist-info/top_level.txt
opsworkstool/__init__.py
opsworkstool/cf_import_things.py
opsworkstool/command.py
opsworkstool/opsworks_creator.py
opsworkstool/opsworks_deployer.py
opsworkstool/parts.py
opsworkstool/stack_tool.py
opsworkstool/template_creator.py
opsworkstool/utility.py
opsworkstool/template/simple/.opsworkstool
opsworkstool/template/simple/template.json
opsworkstool/template/simple/config/config.ini
opsworkstool/template/simple/utility/__init__.py
opsworkstool/template/simple/utility/tools.py
