Metadata-Version: 2.1
Name: OpsworksTool
Version: 0.0.2
Summary: UNKNOWN
Home-page: https://github.com/rubelwi/opsworks-tool
Author: Will Rubel
Author-email: willrubel@gmail.com
License: UNKNOWN
Platform: UNKNOWN
Requires-Dist: boto3 (>=1.4.3)
Requires-Dist: GitPython (>=2.1.7)
Requires-Dist: Click (>=6.7)
Requires-Dist: PyYAML (>=3.12)
Requires-Dist: pymongo (>=3.4.0)
Requires-Dist: stackility (>=0.3)
Requires-Dist: Mako (>=1.0.6)
